heycli/__init__.py
heycli/main.py
heycli-1.0.1.dist-info/METADATA
heycli-1.0.1.dist-info/WHEEL
heycli-1.0.1.dist-info/entry_points.txt
heycli-1.0.1.dist-info/RECORD
