Metadata-Version: 2.4
Name: heycli
Version: 1.0.1
Summary: Your AI Buddy for Daily Tasks
Project-URL: Homepage, https://github.com/sir-kokabi/heycli
Project-URL: Repository, https://github.com/sir-kokabi/heycli
Project-URL: Issues, https://github.com/sir-kokabi/heycli/issues
Author-email: Ayub Kokabi <sir.kokabi@gmail.com>
Maintainer-email: Ayub Kokabi <sir.kokabi@gmail.com>
License-Expression: MIT
Keywords: ai,ai-assistant,artificial-intelligence,assistant,automation,chatbot,cli,code-assistant,command-line,developer-tools,file-management,gpt,natural-language,productivity,python-cli,system-tools,task-automation,terminal,terminal-assistant,workflow
Classifier: Development Status :: 4 - Beta
Classifier: Intended Audience :: Developers
Classifier: Intended Audience :: End Users/Desktop
Classifier: Intended Audience :: Information Technology
Classifier: Intended Audience :: Other Audience
Classifier: Intended Audience :: System Administrators
Classifier: License :: OSI Approved :: MIT License
Classifier: Operating System :: OS Independent
Classifier: Programming Language :: Python :: 3
Classifier: Programming Language :: Python :: 3.9
Classifier: Programming Language :: Python :: 3.10
Classifier: Programming Language :: Python :: 3.11
Classifier: Programming Language :: Python :: 3.12
Classifier: Programming Language :: Python :: 3.13
Classifier: Programming Language :: Python :: 3.14
Classifier: Topic :: Software Development :: Code Generators
Classifier: Topic :: System :: Shells
Classifier: Topic :: System :: System Shells
Classifier: Topic :: System :: Systems Administration
Classifier: Topic :: Utilities
Requires-Python: >=3.9
Requires-Dist: httpx==0.28.1
Requires-Dist: litellm==1.63.3
Requires-Dist: pyyaml==6.0.2
Requires-Dist: questionary==2.1.0
Requires-Dist: rich==13.9.4
Requires-Dist: typer==0.15.2
Requires-Dist: typing-extensions==4.12.2
